comentariosemol/__init__.py
comentariosemol/comentariosemol.py
comentariosemol/test_otras.py
comentariosemol-0.1.8.dist-info/LICENSE
comentariosemol-0.1.8.dist-info/METADATA
comentariosemol-0.1.8.dist-info/WHEEL
comentariosemol-0.1.8.dist-info/entry_points.txt
comentariosemol-0.1.8.dist-info/top_level.txt
comentariosemol-0.1.8.dist-info/RECORD
