Metadata-Version: 2.1
Name: comentariosemol
Version: 0.1.8
Summary: Extrae los comentarios de las noticias de EMOL en formato csv
Home-page: https://github.com/corvalanlara/comentariosemol
Author: Daniel Corvalán
Author-email: corvalanlara@protonmail.com
License: GPLv3
Platform: UNKNOWN
Classifier: Environment :: Console
Classifier: Programming Language :: Python :: 2.7
Classifier: Programming Language :: Python :: 3
Classifier: Programming Language :: Python :: 3.6
Classifier: License :: OSI Approved :: GNU General Public License v3 (GPLv3)
Classifier: Operating System :: OS Independent
Classifier: Development Status :: 3 - Alpha
Classifier: Topic :: Documentation
Requires-Dist: beautifulsoup4
Requires-Dist: selenium
